[
    {
        "goal": "Sort the \"hardware\" list by the following fields:\n - Asset function (descending)\n - State (ascending)",
        "sort_dirs": [
            "desc",
            "asc"
        ],
        "sort_fields": [
            "asset_function",
            "install_status"
        ]
    },
    {
        "goal": "Sort the \"hardware\" list by the following fields:\n - Installed (ascending)\n - Order received (descending)",
        "sort_dirs": [
            "asc",
            "desc"
        ],
        "sort_fields": [
            "install_date",
            "delivery_date"
        ]
    },
    {
        "goal": "Sort the \"hardware\" list by the following fields:\n - Residual value (ascending)\n - Life Cycle Stage Status (descending)",
        "sort_dirs": [
            "asc",
            "desc"
        ],
        "sort_fields": [
            "residual",
            "life_cycle_stage_status"
        ]
    },
    {
        "goal": "Sort the \"hardware\" list by the following fields:\n - Beneficiary (ascending)\n - Assigned to (descending)",
        "sort_dirs": [
            "asc",
            "desc"
        ],
        "sort_fields": [
            "beneficiary",
            "assigned_to"
        ]
    },
    {
        "goal": "Sort the \"hardware\" list by the following fields:\n - Skip sync (ascending)\n - Request line (descending)",
        "sort_dirs": [
            "asc",
            "desc"
        ],
        "sort_fields": [
            "skip_sync",
            "request_line"
        ]
    },
    {
        "goal": "Sort the \"hardware\" list by the following fields:\n - Work notes (ascending)\n - Updates (descending)",
        "sort_dirs": [
            "asc",
            "desc"
        ],
        "sort_fields": [
            "work_notes",
            "sys_mod_count"
        ]
    },
    {
        "goal": "Sort the \"hardware\" list by the following fields:\n - Product instance identifier (ascending)\n - Serial number (descending)",
        "sort_dirs": [
            "asc",
            "desc"
        ],
        "sort_fields": [
            "product_instance_id",
            "serial_number"
        ]
    },
    {
        "goal": "Sort the \"hardware\" list by the following fields:\n - Substate (ascending)\n - Life Cycle Stage (descending)",
        "sort_dirs": [
            "asc",
            "desc"
        ],
        "sort_fields": [
            "substatus",
            "life_cycle_stage"
        ]
    },
    {
        "goal": "Sort the \"hardware\" list by the following fields:\n - Disposal reason (ascending)\n - Supported by (descending)",
        "sort_dirs": [
            "asc",
            "desc"
        ],
        "sort_fields": [
            "disposal_reason",
            "supported_by"
        ]
    },
    {
        "goal": "Sort the \"hardware\" list by the following fields:\n - Depreciation effective date (descending)\n - Comments (descending)",
        "sort_dirs": [
            "desc",
            "desc"
        ],
        "sort_fields": [
            "depreciation_date",
            "comments"
        ]
    },
    {
        "goal": "Sort the \"hardware\" list by the following fields:\n - Residual date (ascending)\n - Acquisition method (ascending)",
        "sort_dirs": [
            "asc",
            "asc"
        ],
        "sort_fields": [
            "residual_date",
            "acquisition_method"
        ]
    },
    {
        "goal": "Sort the \"hardware\" list by the following fields:\n - Depreciation effective date (descending)\n - Old substatus (ascending)",
        "sort_dirs": [
            "desc",
            "asc"
        ],
        "sort_fields": [
            "depreciation_date",
            "old_substatus"
        ]
    },
    {
        "goal": "Sort the \"hardware\" list by the following fields:\n - Product instance identifier (descending)\n - Created by (descending)",
        "sort_dirs": [
            "desc",
            "desc"
        ],
        "sort_fields": [
            "product_instance_id",
            "sys_created_by"
        ]
    },
    {
        "goal": "Sort the \"hardware\" list by the following fields:\n - Skip sync (ascending)\n - Depreciation (ascending)",
        "sort_dirs": [
            "asc",
            "asc"
        ],
        "sort_fields": [
            "skip_sync",
            "depreciation"
        ]
    },
    {
        "goal": "Sort the \"hardware\" list by the following fields:\n - Model (descending)\n - Tags (descending)",
        "sort_dirs": [
            "desc",
            "desc"
        ],
        "sort_fields": [
            "model",
            "sys_tags"
        ]
    },
    {
        "goal": "Sort the \"hardware\" list by the following fields:\n - Created (descending)\n - Old status (ascending)",
        "sort_dirs": [
            "desc",
            "asc"
        ],
        "sort_fields": [
            "sys_created_on",
            "old_status"
        ]
    },
    {
        "goal": "Sort the \"hardware\" list by the following fields:\n - Skip sync (ascending)\n - Model category (descending)",
        "sort_dirs": [
            "asc",
            "desc"
        ],
        "sort_fields": [
            "skip_sync",
            "model_category"
        ]
    },
    {
        "goal": "Sort the \"hardware\" list by the following fields:\n - Retired date (descending)\n - Support group (descending)",
        "sort_dirs": [
            "desc",
            "desc"
        ],
        "sort_fields": [
            "retired",
            "support_group"
        ]
    },
    {
        "goal": "Sort the \"hardware\" list by the following fields:\n - Updated by (ascending)\n - Quantity (ascending)",
        "sort_dirs": [
            "asc",
            "asc"
        ],
        "sort_fields": [
            "sys_updated_by",
            "quantity"
        ]
    },
    {
        "goal": "Sort the \"hardware\" list by the following fields:\n - Model (ascending)\n - State (ascending)",
        "sort_dirs": [
            "asc",
            "asc"
        ],
        "sort_fields": [
            "model",
            "install_status"
        ]
    },
    {
        "goal": "Sort the \"hardware\" list by the following fields:\n - Resold value (ascending)\n - Depreciated amount (ascending)",
        "sort_dirs": [
            "asc",
            "asc"
        ],
        "sort_fields": [
            "resold_value",
            "depreciated_amount"
        ]
    },
    {
        "goal": "Sort the \"hardware\" list by the following fields:\n - Beneficiary (descending)\n - Tags (ascending)",
        "sort_dirs": [
            "desc",
            "asc"
        ],
        "sort_fields": [
            "beneficiary",
            "sys_tags"
        ]
    },
    {
        "goal": "Sort the \"hardware\" list by the following fields:\n - Cost (ascending)\n - Location (ascending)",
        "sort_dirs": [
            "asc",
            "asc"
        ],
        "sort_fields": [
            "cost",
            "location"
        ]
    },
    {
        "goal": "Sort the \"hardware\" list by the following fields:\n - Request line (descending)\n - Managed by (ascending)",
        "sort_dirs": [
            "desc",
            "asc"
        ],
        "sort_fields": [
            "request_line",
            "managed_by"
        ]
    },
    {
        "goal": "Sort the \"hardware\" list by the following fields:\n - Sys ID (ascending)\n - Configuration Item (ascending)",
        "sort_dirs": [
            "asc",
            "asc"
        ],
        "sort_fields": [
            "sys_id",
            "ci"
        ]
    },
    {
        "goal": "Sort the \"hardware\" list by the following fields:\n - Domain (descending)\n - Reserved for (descending)",
        "sort_dirs": [
            "desc",
            "desc"
        ],
        "sort_fields": [
            "sys_domain",
            "reserved_for"
        ]
    },
    {
        "goal": "Sort the \"hardware\" list by the following fields:\n - Beneficiary (descending)\n - State (descending)",
        "sort_dirs": [
            "desc",
            "desc"
        ],
        "sort_fields": [
            "beneficiary",
            "install_status"
        ]
    },
    {
        "goal": "Sort the \"hardware\" list by the following fields:\n - Installed (descending)\n - Checked in (ascending)",
        "sort_dirs": [
            "desc",
            "asc"
        ],
        "sort_fields": [
            "install_date",
            "checked_in"
        ]
    },
    {
        "goal": "Sort the \"hardware\" list by the following fields:\n - Pre-allocated (descending)\n - Active transfer order (descending)",
        "sort_dirs": [
            "desc",
            "desc"
        ],
        "sort_fields": [
            "pre_allocated",
            "active_to"
        ]
    },
    {
        "goal": "Sort the \"hardware\" list by the following fields:\n - Due in (ascending)\n - Old status (descending)",
        "sort_dirs": [
            "asc",
            "desc"
        ],
        "sort_fields": [
            "due_in",
            "old_status"
        ]
    },
    {
        "goal": "Sort the \"hardware\" list by the following fields:\n - Vendor (descending)\n - Old status (ascending)",
        "sort_dirs": [
            "desc",
            "asc"
        ],
        "sort_fields": [
            "vendor",
            "old_status"
        ]
    },
    {
        "goal": "Sort the \"hardware\" list by the following fields:\n - Vendor (ascending)\n - Configuration Item (descending)",
        "sort_dirs": [
            "asc",
            "desc"
        ],
        "sort_fields": [
            "vendor",
            "ci"
        ]
    },
    {
        "goal": "Sort the \"hardware\" list by the following fields:\n - Request line (ascending)\n - Class (ascending)",
        "sort_dirs": [
            "asc",
            "asc"
        ],
        "sort_fields": [
            "request_line",
            "sys_class_name"
        ]
    },
    {
        "goal": "Sort the \"hardware\" list by the following fields:\n - Due in (descending)\n - Class (descending)",
        "sort_dirs": [
            "desc",
            "desc"
        ],
        "sort_fields": [
            "due_in",
            "sys_class_name"
        ]
    },
    {
        "goal": "Sort the \"hardware\" list by the following fields:\n - Warranty expiration (ascending)\n - Managed by (ascending)",
        "sort_dirs": [
            "asc",
            "asc"
        ],
        "sort_fields": [
            "warranty_expiration",
            "managed_by"
        ]
    },
    {
        "goal": "Sort the \"hardware\" list by the following fields:\n - Request line (descending)\n - Model (descending)",
        "sort_dirs": [
            "desc",
            "desc"
        ],
        "sort_fields": [
            "request_line",
            "model"
        ]
    },
    {
        "goal": "Sort the \"hardware\" list by the following fields:\n - Stockroom (ascending)\n - Quantity (descending)",
        "sort_dirs": [
            "asc",
            "desc"
        ],
        "sort_fields": [
            "stockroom",
            "quantity"
        ]
    },
    {
        "goal": "Sort the \"hardware\" list by the following fields:\n - Skip sync (ascending)\n - Beneficiary (ascending)",
        "sort_dirs": [
            "asc",
            "asc"
        ],
        "sort_fields": [
            "skip_sync",
            "beneficiary"
        ]
    },
    {
        "goal": "Sort the \"hardware\" list by the following fields:\n - Warranty expiration (descending)\n - PO number (descending)",
        "sort_dirs": [
            "desc",
            "desc"
        ],
        "sort_fields": [
            "warranty_expiration",
            "po_number"
        ]
    },
    {
        "goal": "Sort the \"hardware\" list by the following fields:\n - Stockroom (ascending)\n - Company (descending)",
        "sort_dirs": [
            "asc",
            "desc"
        ],
        "sort_fields": [
            "stockroom",
            "company"
        ]
    },
    {
        "goal": "Sort the \"hardware\" list by the following fields:\n - Acquisition method (ascending)\n - Old substatus (descending)",
        "sort_dirs": [
            "asc",
            "desc"
        ],
        "sort_fields": [
            "acquisition_method",
            "old_substatus"
        ]
    },
    {
        "goal": "Sort the \"hardware\" list by the following fields:\n - Owned by (ascending)\n - Purchased (descending)",
        "sort_dirs": [
            "asc",
            "desc"
        ],
        "sort_fields": [
            "owned_by",
            "purchase_date"
        ]
    },
    {
        "goal": "Sort the \"hardware\" list by the following fields:\n - Checked out (descending)\n - Salvage value (ascending)",
        "sort_dirs": [
            "desc",
            "asc"
        ],
        "sort_fields": [
            "checked_out",
            "salvage_value"
        ]
    },
    {
        "goal": "Sort the \"hardware\" list by the following fields:\n - Created (ascending)\n - Depreciation (descending)",
        "sort_dirs": [
            "asc",
            "desc"
        ],
        "sort_fields": [
            "sys_created_on",
            "depreciation"
        ]
    },
    {
        "goal": "Sort the \"hardware\" list by the following fields:\n - Residual value (ascending)\n - Substate (descending)",
        "sort_dirs": [
            "asc",
            "desc"
        ],
        "sort_fields": [
            "residual",
            "substatus"
        ]
    },
    {
        "goal": "Sort the \"hardware\" list by the following fields:\n - Life Cycle Stage Status (ascending)\n - Eligible for refresh (ascending)",
        "sort_dirs": [
            "asc",
            "asc"
        ],
        "sort_fields": [
            "life_cycle_stage_status",
            "eligible_for_refresh"
        ]
    },
    {
        "goal": "Sort the \"hardware\" list by the following fields:\n - Tags (descending)\n - Salvage value (descending)",
        "sort_dirs": [
            "desc",
            "desc"
        ],
        "sort_fields": [
            "sys_tags",
            "salvage_value"
        ]
    },
    {
        "goal": "Sort the \"hardware\" list by the following fields:\n - Justification (ascending)\n - Reserved for (ascending)",
        "sort_dirs": [
            "asc",
            "asc"
        ],
        "sort_fields": [
            "justification",
            "reserved_for"
        ]
    },
    {
        "goal": "Sort the \"hardware\" list by the following fields:\n - Model (descending)\n - Retired date (ascending)",
        "sort_dirs": [
            "desc",
            "asc"
        ],
        "sort_fields": [
            "model",
            "retired"
        ]
    },
    {
        "goal": "Sort the \"hardware\" list by the following fields:\n - Updated (ascending)\n - Old status (descending)",
        "sort_dirs": [
            "asc",
            "desc"
        ],
        "sort_fields": [
            "sys_updated_on",
            "old_status"
        ]
    },
    {
        "goal": "Sort the \"hardware\" list by the following fields:\n - Created by (ascending)\n - Eligible for refresh (descending)",
        "sort_dirs": [
            "asc",
            "desc"
        ],
        "sort_fields": [
            "sys_created_by",
            "eligible_for_refresh"
        ]
    },
    {
        "goal": "Sort the \"hardware\" list by the following fields:\n - Updates (descending)\n - Location (ascending)",
        "sort_dirs": [
            "desc",
            "asc"
        ],
        "sort_fields": [
            "sys_mod_count",
            "location"
        ]
    },
    {
        "goal": "Sort the \"hardware\" list by the following fields:\n - Resale price (ascending)\n - Acquisition method (descending)",
        "sort_dirs": [
            "asc",
            "desc"
        ],
        "sort_fields": [
            "resale_price",
            "acquisition_method"
        ]
    },
    {
        "goal": "Sort the \"hardware\" list by the following fields:\n - Request line (descending)\n - Serial number (descending)",
        "sort_dirs": [
            "desc",
            "desc"
        ],
        "sort_fields": [
            "request_line",
            "serial_number"
        ]
    },
    {
        "goal": "Sort the \"hardware\" list by the following fields:\n - Sys ID (ascending)\n - Due (ascending)",
        "sort_dirs": [
            "asc",
            "asc"
        ],
        "sort_fields": [
            "sys_id",
            "due"
        ]
    },
    {
        "goal": "Sort the \"hardware\" list by the following fields:\n - Product instance identifier (ascending)\n - Substate (ascending)",
        "sort_dirs": [
            "asc",
            "asc"
        ],
        "sort_fields": [
            "product_instance_id",
            "substatus"
        ]
    },
    {
        "goal": "Sort the \"hardware\" list by the following fields:\n - Substate (ascending)\n - Display name (ascending)",
        "sort_dirs": [
            "asc",
            "asc"
        ],
        "sort_fields": [
            "substatus",
            "display_name"
        ]
    },
    {
        "goal": "Sort the \"hardware\" list by the following fields:\n - Purchased (ascending)\n - Lease contract (ascending)",
        "sort_dirs": [
            "asc",
            "asc"
        ],
        "sort_fields": [
            "purchase_date",
            "lease_id"
        ]
    },
    {
        "goal": "Sort the \"hardware\" list by the following fields:\n - Asset function (descending)\n - Quantity (ascending)",
        "sort_dirs": [
            "desc",
            "asc"
        ],
        "sort_fields": [
            "asset_function",
            "quantity"
        ]
    },
    {
        "goal": "Sort the \"hardware\" list by the following fields:\n - Old status (descending)\n - Reserved for (ascending)",
        "sort_dirs": [
            "desc",
            "asc"
        ],
        "sort_fields": [
            "old_status",
            "reserved_for"
        ]
    },
    {
        "goal": "Sort the \"hardware\" list by the following fields:\n - Pre-allocated (descending)\n - Ordered (descending)",
        "sort_dirs": [
            "desc",
            "desc"
        ],
        "sort_fields": [
            "pre_allocated",
            "order_date"
        ]
    },
    {
        "goal": "Sort the \"hardware\" list by the following fields:\n - Residual date (ascending)\n - Configuration Item (descending)",
        "sort_dirs": [
            "asc",
            "desc"
        ],
        "sort_fields": [
            "residual_date",
            "ci"
        ]
    },
    {
        "goal": "Sort the \"hardware\" list by the following fields:\n - Assigned (ascending)\n - Work notes (descending)",
        "sort_dirs": [
            "asc",
            "desc"
        ],
        "sort_fields": [
            "assigned",
            "work_notes"
        ]
    },
    {
        "goal": "Sort the \"hardware\" list by the following fields:\n - Assigned to (ascending)\n - Tags (descending)",
        "sort_dirs": [
            "asc",
            "desc"
        ],
        "sort_fields": [
            "assigned_to",
            "sys_tags"
        ]
    },
    {
        "goal": "Sort the \"hardware\" list by the following fields:\n - Depreciated amount (descending)\n - Depreciation (ascending)",
        "sort_dirs": [
            "desc",
            "asc"
        ],
        "sort_fields": [
            "depreciated_amount",
            "depreciation"
        ]
    },
    {
        "goal": "Sort the \"hardware\" list by the following fields:\n - Parent (descending)\n - Department (descending)",
        "sort_dirs": [
            "desc",
            "desc"
        ],
        "sort_fields": [
            "parent",
            "department"
        ]
    },
    {
        "goal": "Sort the \"hardware\" list by the following fields:\n - Domain Path (descending)\n - Lease contract (ascending)",
        "sort_dirs": [
            "desc",
            "asc"
        ],
        "sort_fields": [
            "sys_domain_path",
            "lease_id"
        ]
    },
    {
        "goal": "Sort the \"hardware\" list by the following fields:\n - Cost center (descending)\n - Expenditure type (descending)",
        "sort_dirs": [
            "desc",
            "desc"
        ],
        "sort_fields": [
            "cost_center",
            "expenditure_type"
        ]
    },
    {
        "goal": "Sort the \"hardware\" list by the following fields:\n - Updated (ascending)\n - Location (descending)",
        "sort_dirs": [
            "asc",
            "desc"
        ],
        "sort_fields": [
            "sys_updated_on",
            "location"
        ]
    },
    {
        "goal": "Sort the \"hardware\" list by the following fields:\n - Order received (descending)\n - Assigned (ascending)",
        "sort_dirs": [
            "desc",
            "asc"
        ],
        "sort_fields": [
            "delivery_date",
            "assigned"
        ]
    },
    {
        "goal": "Sort the \"hardware\" list by the following fields:\n - Pre-allocated (descending)\n - Supported by (ascending)",
        "sort_dirs": [
            "desc",
            "asc"
        ],
        "sort_fields": [
            "pre_allocated",
            "supported_by"
        ]
    },
    {
        "goal": "Sort the \"hardware\" list by the following fields:\n - Expenditure type (ascending)\n - Cost (descending)",
        "sort_dirs": [
            "asc",
            "desc"
        ],
        "sort_fields": [
            "expenditure_type",
            "cost"
        ]
    },
    {
        "goal": "Sort the \"hardware\" list by the following fields:\n - Model component (ascending)\n - Assigned to (ascending)",
        "sort_dirs": [
            "asc",
            "asc"
        ],
        "sort_fields": [
            "model_component_id",
            "assigned_to"
        ]
    },
    {
        "goal": "Sort the \"hardware\" list by the following fields:\n - Updated by (descending)\n - Acquisition method (ascending)",
        "sort_dirs": [
            "desc",
            "asc"
        ],
        "sort_fields": [
            "sys_updated_by",
            "acquisition_method"
        ]
    },
    {
        "goal": "Sort the \"hardware\" list by the following fields:\n - Order received (descending)\n - Stockroom (descending)",
        "sort_dirs": [
            "desc",
            "desc"
        ],
        "sort_fields": [
            "delivery_date",
            "stockroom"
        ]
    },
    {
        "goal": "Sort the \"hardware\" list by the following fields:\n - Model category (ascending)\n - Domain Path (descending)",
        "sort_dirs": [
            "asc",
            "desc"
        ],
        "sort_fields": [
            "model_category",
            "sys_domain_path"
        ]
    },
    {
        "goal": "Sort the \"hardware\" list by the following fields:\n - Life Cycle Stage (ascending)\n - Old substatus (ascending)",
        "sort_dirs": [
            "asc",
            "asc"
        ],
        "sort_fields": [
            "life_cycle_stage",
            "old_substatus"
        ]
    },
    {
        "goal": "Sort the \"hardware\" list by the following fields:\n - Depreciation effective date (ascending)\n - Quantity (descending)",
        "sort_dirs": [
            "asc",
            "desc"
        ],
        "sort_fields": [
            "depreciation_date",
            "quantity"
        ]
    },
    {
        "goal": "Sort the \"hardware\" list by the following fields:\n - GL account (ascending)\n - PO number (descending)",
        "sort_dirs": [
            "asc",
            "desc"
        ],
        "sort_fields": [
            "gl_account",
            "po_number"
        ]
    },
    {
        "goal": "Sort the \"hardware\" list by the following fields:\n - Company (descending)\n - Location (descending)",
        "sort_dirs": [
            "desc",
            "desc"
        ],
        "sort_fields": [
            "company",
            "location"
        ]
    },
    {
        "goal": "Sort the \"hardware\" list by the following fields:\n - Work notes (ascending)\n - Cost (descending)",
        "sort_dirs": [
            "asc",
            "desc"
        ],
        "sort_fields": [
            "work_notes",
            "cost"
        ]
    },
    {
        "goal": "Sort the \"hardware\" list by the following fields:\n - State (ascending)\n - Serial number (descending)",
        "sort_dirs": [
            "asc",
            "desc"
        ],
        "sort_fields": [
            "install_status",
            "serial_number"
        ]
    },
    {
        "goal": "Sort the \"hardware\" list by the following fields:\n - Beneficiary (ascending)\n - State (ascending)",
        "sort_dirs": [
            "asc",
            "asc"
        ],
        "sort_fields": [
            "beneficiary",
            "install_status"
        ]
    },
    {
        "goal": "Sort the \"hardware\" list by the following fields:\n - Order received (ascending)\n - Checked in (ascending)",
        "sort_dirs": [
            "asc",
            "asc"
        ],
        "sort_fields": [
            "delivery_date",
            "checked_in"
        ]
    },
    {
        "goal": "Sort the \"hardware\" list by the following fields:\n - Life Cycle Stage Status (descending)\n - Old status (descending)",
        "sort_dirs": [
            "desc",
            "desc"
        ],
        "sort_fields": [
            "life_cycle_stage_status",
            "old_status"
        ]
    },
    {
        "goal": "Sort the \"hardware\" list by the following fields:\n - GL account (ascending)\n - Assigned (descending)",
        "sort_dirs": [
            "asc",
            "desc"
        ],
        "sort_fields": [
            "gl_account",
            "assigned"
        ]
    },
    {
        "goal": "Sort the \"hardware\" list by the following fields:\n - Asset tag (ascending)\n - Model component (ascending)",
        "sort_dirs": [
            "asc",
            "asc"
        ],
        "sort_fields": [
            "asset_tag",
            "model_component_id"
        ]
    },
    {
        "goal": "Sort the \"hardware\" list by the following fields:\n - Model (descending)\n - Quantity (ascending)",
        "sort_dirs": [
            "desc",
            "asc"
        ],
        "sort_fields": [
            "model",
            "quantity"
        ]
    },
    {
        "goal": "Sort the \"hardware\" list by the following fields:\n - Residual value (descending)\n - Updates (descending)",
        "sort_dirs": [
            "desc",
            "desc"
        ],
        "sort_fields": [
            "residual",
            "sys_mod_count"
        ]
    },
    {
        "goal": "Sort the \"hardware\" list by the following fields:\n - Invoice number (ascending)\n - Depreciated amount (descending)",
        "sort_dirs": [
            "asc",
            "desc"
        ],
        "sort_fields": [
            "invoice_number",
            "depreciated_amount"
        ]
    },
    {
        "goal": "Sort the \"hardware\" list by the following fields:\n - Scheduled retirement (ascending)\n - Active transfer order (descending)",
        "sort_dirs": [
            "asc",
            "desc"
        ],
        "sort_fields": [
            "retirement_date",
            "active_to"
        ]
    },
    {
        "goal": "Sort the \"hardware\" list by the following fields:\n - Model (descending)\n - Depreciation (descending)",
        "sort_dirs": [
            "desc",
            "desc"
        ],
        "sort_fields": [
            "model",
            "depreciation"
        ]
    },
    {
        "goal": "Sort the \"hardware\" list by the following fields:\n - Model component (ascending)\n - Salvage value (descending)",
        "sort_dirs": [
            "asc",
            "desc"
        ],
        "sort_fields": [
            "model_component_id",
            "salvage_value"
        ]
    },
    {
        "goal": "Sort the \"hardware\" list by the following fields:\n - PO number (ascending)\n - Depreciation effective date (ascending)",
        "sort_dirs": [
            "asc",
            "asc"
        ],
        "sort_fields": [
            "po_number",
            "depreciation_date"
        ]
    },
    {
        "goal": "Sort the \"hardware\" list by the following fields:\n - Company (descending)\n - Retired date (descending)",
        "sort_dirs": [
            "desc",
            "desc"
        ],
        "sort_fields": [
            "company",
            "retired"
        ]
    },
    {
        "goal": "Sort the \"hardware\" list by the following fields:\n - Cost (descending)\n - Serial number (descending)",
        "sort_dirs": [
            "desc",
            "desc"
        ],
        "sort_fields": [
            "cost",
            "serial_number"
        ]
    },
    {
        "goal": "Sort the \"hardware\" list by the following fields:\n - Owned by (ascending)\n - Expenditure type (descending)",
        "sort_dirs": [
            "asc",
            "desc"
        ],
        "sort_fields": [
            "owned_by",
            "expenditure_type"
        ]
    },
    {
        "goal": "Sort the \"hardware\" list by the following fields:\n - Depreciated amount (descending)\n - Cost center (descending)",
        "sort_dirs": [
            "desc",
            "desc"
        ],
        "sort_fields": [
            "depreciated_amount",
            "cost_center"
        ]
    },
    {
        "goal": "Sort the \"hardware\" list by the following fields:\n - Skip sync (descending)\n - Stockroom (ascending)",
        "sort_dirs": [
            "desc",
            "asc"
        ],
        "sort_fields": [
            "skip_sync",
            "stockroom"
        ]
    },
    {
        "goal": "Sort the \"hardware\" list by the following fields:\n - Cost center (descending)\n - Support group (ascending)",
        "sort_dirs": [
            "desc",
            "asc"
        ],
        "sort_fields": [
            "cost_center",
            "support_group"
        ]
    }
]